gradio_richtext/__init__.py
gradio_richtext/richtext.py
gradio_richtext/richtext.pyi
gradio_richtext/templates/component/Index-C6h55__v.js
gradio_richtext/templates/component/_basePickBy-CAaUS-8r.js
gradio_richtext/templates/component/_baseUniq-DjA55hWa.js
gradio_richtext/templates/component/arc-DfOiB_XE.js
gradio_richtext/templates/component/architectureDiagram-SUXI7LT5-DGaidlmh.js
gradio_richtext/templates/component/auto-render-BwaQGe8P.js
gradio_richtext/templates/component/blank-line-C74Di3OL.js
gradio_richtext/templates/component/blockDiagram-6J76NXCF-D6ByUYXJ.js
gradio_richtext/templates/component/c4Diagram-6F6E4RAY-B-h4KFHk.js
gradio_richtext/templates/component/channel-CJYGSLSg.js
gradio_richtext/templates/component/chunk-353BL4L5-CR1fausW.js
gradio_richtext/templates/component/chunk-67H74DCK-DJSG38o7.js
gradio_richtext/templates/component/chunk-AACKK3MU-BhtfruCE.js
gradio_richtext/templates/component/chunk-BFAMUDN2-dGjnXn7o.js
gradio_richtext/templates/component/chunk-E2GYISFI-XYTqF-_O.js
gradio_richtext/templates/component/chunk-OW32GOEJ-D1DDwhWQ.js
gradio_richtext/templates/component/chunk-SKB7J2MH-BzqU1Sio.js
gradio_richtext/templates/component/chunk-SZ463SBG-BOOGMI08.js
gradio_richtext/templates/component/classDiagram-M3E45YP4-DTAxcaHk.js
gradio_richtext/templates/component/classDiagram-v2-YAWTLIQI-DTAxcaHk.js
gradio_richtext/templates/component/clone-CWGPaPUO.js
gradio_richtext/templates/component/cytoscape.esm-CphbmbIK.js
gradio_richtext/templates/component/dagre-JOIXM2OF-61uHqHKr.js
gradio_richtext/templates/component/default-BwQc_qtq.js
gradio_richtext/templates/component/defaultLocale-D7EN2tov.js
gradio_richtext/templates/component/diagram-5UYTHUR4-DO6DSx9a.js
gradio_richtext/templates/component/diagram-VMROVX33-BAb6JSmo.js
gradio_richtext/templates/component/diagram-ZTM2IBQH-DcagKXu5.js
gradio_richtext/templates/component/erDiagram-3M52JZNH-BrGhy0XA.js
gradio_richtext/templates/component/flowDiagram-KYDEHFYC-CZVI0ejk.js
gradio_richtext-0.0.8.dist-info/METADATA
gradio_richtext-0.0.8.dist-info/WHEEL
gradio_richtext-0.0.8.dist-info/RECORD
